main.py
appmatic-0.1.0.dist-info/METADATA
appmatic-0.1.0.dist-info/WHEEL
appmatic-0.1.0.dist-info/top_level.txt
appmatic-0.1.0.dist-info/RECORD
