Metadata-Version: 2.4
Name: appmatic
Version: 0.1.0
Summary: full stack, multi-platform app framework for python
Requires-Python: >=3.11
